mpl_panel_builder/__init__.py
mpl_panel_builder/config.py
mpl_panel_builder/panel.py
mpl_panel_builder/py.typed
mpl_panel_builder/features/__init__.py
mpl_panel_builder/features/annotation.py
mpl_panel_builder/features/colorbar.py
mpl_panel_builder/features/gridlines.py
mpl_panel_builder/features/label.py
mpl_panel_builder/features/scalebar.py
mpl_panel_builder/helpers/__init__.py
mpl_panel_builder/helpers/examples.py
mpl_panel_builder/helpers/mpl.py
mpl_panel_builder-0.6.2.dist-info/METADATA
mpl_panel_builder-0.6.2.dist-info/WHEEL
mpl_panel_builder-0.6.2.dist-info/licenses/LICENSE
mpl_panel_builder-0.6.2.dist-info/RECORD
