Metadata-Version: 2.4
Name: mpl-panel-builder
Version: 0.6.2
Summary: Matplotlib based figure panel builder
Project-URL: Homepage, https://github.com/NoviaIntSysGroup/mpl-panel-builder
Project-URL: Repository, https://github.com/NoviaIntSysGroup/mpl-panel-builder
Author-email: Johan Westö <johan.westo@gmail.com>
License: MIT License
License-File: LICENSE
Requires-Python: >=3.11
Requires-Dist: matplotlib>=3.10.3
